dremio_client/__init__.py
dremio_client/cli.py
dremio_client/dremio_client.py
dremio_client/dremio_simple_client.py
dremio_client/error.py
dremio_client/odbc.py
dremio_client/query.py
dremio_client/auth/__init__.py
dremio_client/auth/basic.py
dremio_client/auth/config.py
dremio_client/cloner/read_config/config.yaml
dremio_client/cloner/write_config/config.yaml
dremio_client/conf/__init__.py
dremio_client/conf/cli_helper.py
dremio_client/conf/config_default.yaml
dremio_client/conf/config_parser.py
dremio_client/flight/__init__.py
dremio_client/flight/command_pb2.py
dremio_client/flight/flight_auth.py
dremio_client/model/__init__.py
dremio_client/model/catalog.py
dremio_client/model/data.py
dremio_client/model/endpoints.py
dremio_client/util/__init__.py
dremio_client/util/delete.py
dremio_client/util/io.py
dremio_client/util/promote.py
dremio_client/util/query.py
dremio_client/util/refresh.py
dremio_client-0.15.1.dist-info/AUTHORS.rst
dremio_client-0.15.1.dist-info/LICENSE
dremio_client-0.15.1.dist-info/METADATA
dremio_client-0.15.1.dist-info/WHEEL
dremio_client-0.15.1.dist-info/entry_points.txt
dremio_client-0.15.1.dist-info/top_level.txt
dremio_client-0.15.1.dist-info/RECORD
