Metadata-Version: 2.1
Name: dremio-client
Version: 0.15.1
Summary: Python client for Dremio. See https://dremio.com
Home-page: https://github.com/rymurr/dremio_client
Author: Ryan Murray
Author-email: rymurr@gmail.com
License: Apache Software License 2.0
Keywords: dremio_client
Platform: UNKNOWN
Classifier: Development Status :: 2 - Pre-Alpha
Classifier: Intended Audience :: Developers
Classifier: License :: OSI Approved :: Apache Software License
Classifier: Natural Language :: English
Classifier: Programming Language :: Python :: 2
Classifier: Programming Language :: Python :: 2.7
Classifier: Programming Language :: Python :: 3
Classifier: Programming Language :: Python :: 3.4
Classifier: Programming Language :: Python :: 3.5
Classifier: Programming Language :: Python :: 3.6
Classifier: Programming Language :: Python :: 3.7
Requires-Dist: Click (>=6.0)
Requires-Dist: requests (>=2.21.0)
Requires-Dist: confuse
Requires-Dist: simplejson
Requires-Dist: attrs
Requires-Dist: six
Requires-Dist: futures ; python_version == "2.7"
Provides-Extra: full
Requires-Dist: pyarrow (>=0.15.0) ; extra == 'full'
Requires-Dist: pandas (>=0.24.2) ; extra == 'full'
Requires-Dist: requests-futures (==1.0.0) ; extra == 'full'
Requires-Dist: markdown ; extra == 'full'
Provides-Extra: noarrow
Requires-Dist: pandas (>=0.24.2) ; extra == 'noarrow'
Requires-Dist: requests-futures (==1.0.0) ; extra == 'noarrow'
Requires-Dist: markdown ; extra == 'noarrow'
